puffpastry/__init__.py
puffpastry/tests/__init__.py
puffpastry/tests/test_api.py
puffpastry-0.0.3.dist-info/METADATA
puffpastry-0.0.3.dist-info/WHEEL
puffpastry-0.0.3.dist-info/licenses/LICENSE
puffpastry-0.0.3.dist-info/RECORD
