Metadata-Version: 2.3
Name: puffpastry
Version: 0.0.3
Summary: puffpastry - lightweight dependency injection for Python
Project-URL: Homepage, https://github.com/adamhadani/puffpastry
Project-URL: Issues, https://github.com/adamhadani/puffpastry/issues
Author-email: Adam Ever-Hadani <adamhadani@gmail.com>
License-File: LICENSE
Classifier: License :: OSI Approved :: MIT License
Classifier: Operating System :: OS Independent
Classifier: Programming Language :: Python :: 3
Requires-Python: >=3.8
Requires-Dist: python-dotenv>=1.0.1
Provides-Extra: test
Requires-Dist: coverage; extra == 'test'
Requires-Dist: pytest; extra == 'test'
Requires-Dist: pytest-coverage; extra == 'test'
